napari_cellseg3d/__init__.py
napari_cellseg3d/config.py
napari_cellseg3d/interface.py
napari_cellseg3d/napari.yaml
napari_cellseg3d/plugins.py
napari_cellseg3d/setup.py
napari_cellseg3d/utils.py
napari_cellseg3d/_tests/__init__.py
napari_cellseg3d/_tests/conftest.py
napari_cellseg3d/_tests/fixtures.py
napari_cellseg3d/_tests/test_base_plugin.py
napari_cellseg3d/_tests/test_dock_widget.py
napari_cellseg3d/_tests/test_helper.py
napari_cellseg3d/_tests/test_inference.py
napari_cellseg3d/_tests/test_interface.py
napari_cellseg3d/_tests/test_labels_correction.py
napari_cellseg3d/_tests/test_model_framework.py
napari_cellseg3d/_tests/test_models.py
napari_cellseg3d/_tests/test_plugin_inference.py
napari_cellseg3d/_tests/test_plugin_training.py
napari_cellseg3d/_tests/test_plugin_utils.py
napari_cellseg3d/_tests/test_plugins.py
napari_cellseg3d/_tests/test_review.py
napari_cellseg3d/_tests/test_training.py
napari_cellseg3d/_tests/test_utils.py
napari_cellseg3d/_tests/test_weight_download.py
napari_cellseg3d/_tests/test_wnet_training.py
napari_cellseg3d/_tests/res/test.png
napari_cellseg3d/code_models/__init__.py
napari_cellseg3d/code_models/crf.py
napari_cellseg3d/code_models/instance_segmentation.py
napari_cellseg3d/code_models/model_framework.py
napari_cellseg3d/code_models/worker_inference.py
napari_cellseg3d/code_models/worker_training.py
napari_cellseg3d/code_models/workers_utils.py
napari_cellseg3d/code_models/models/TEMPLATE_model.py
napari_cellseg3d/code_models/models/__init__.py
napari_cellseg3d/code_models/models/model_SegResNet.py
napari_cellseg3d/code_models/models/model_SwinUNetR.py
napari_cellseg3d/code_models/models/model_TRAILMAP.py
napari_cellseg3d/code_models/models/model_TRAILMAP_MS.py
napari_cellseg3d/code_models/models/model_VNet.py
napari_cellseg3d/code_models/models/model_WNet.py
napari_cellseg3d/code_models/models/model_test.py
napari_cellseg3d/code_models/models/pretrained/__init__.py
napari_cellseg3d-0.2.2.dist-info/LICENSE
napari_cellseg3d-0.2.2.dist-info/METADATA
napari_cellseg3d-0.2.2.dist-info/WHEEL
napari_cellseg3d-0.2.2.dist-info/entry_points.txt
napari_cellseg3d-0.2.2.dist-info/top_level.txt
napari_cellseg3d-0.2.2.dist-info/RECORD
