Metadata-Version: 2.1
Name: napari_cellseg3d
Version: 0.2.2
Summary: Plugin for cell segmentation in 3D
Author-email: Cyril Achard <cyril.achard@epfl.ch>, Maxime Vidal <maxime.vidal@epfl.ch>, Mackenzie Mathis <mackenzie@post.harvard.edu>
License: MIT
Project-URL: Homepage, https://github.com/AdaptiveMotorControlLab/CellSeg3D
Project-URL: Documentation, https://adaptivemotorcontrollab.github.io/cellseg3d-docs/res/welcome.html
Project-URL: Issues, https://github.com/AdaptiveMotorControlLab/CellSeg3D/issues
Classifier: Development Status :: 4 - Beta
Classifier: Intended Audience :: Science/Research
Classifier: Framework :: napari
Classifier: Topic :: Software Development :: Testing
Classifier: Programming Language :: Python
Classifier: Programming Language :: Python :: 3
Classifier: Programming Language :: Python :: 3.8
Classifier: Programming Language :: Python :: 3.9
Classifier: Programming Language :: Python :: 3.10
Classifier: Operating System :: OS Independent
Classifier: License :: OSI Approved :: MIT License
Classifier: Topic :: Scientific/Engineering :: Artificial Intelligence
Classifier: Topic :: Scientific/Engineering :: Image Processing
Classifier: Topic :: Scientific/Engineering :: Visualization
Requires-Python: >=3.8
License-File: LICENSE
Requires-Dist: numpy
Requires-Dist: napari[all]>=0.4.14
Requires-Dist: QtPy
Requires-Dist: scikit-image>=0.19.2
Requires-Dist: matplotlib>=3.4.1
Requires-Dist: tifffile>=2022.2.9
Requires-Dist: imagecodecs>=2023.3.16
Requires-Dist: torch>=1.11
Requires-Dist: monai[einops,nibabel]>=0.9.0
Requires-Dist: itk
Requires-Dist: tqdm
Requires-Dist: pyclesperanto-prototype
Requires-Dist: tqdm
Requires-Dist: matplotlib
Requires-Dist: pydensecrf2
Provides-Extra: pyqt5
Requires-Dist: pyqt5; extra == "pyqt5"
Provides-Extra: pyside2
Requires-Dist: pyside2; extra == "pyside2"
Provides-Extra: pyside6
Requires-Dist: pyside6; extra == "pyside6"
Provides-Extra: onnx-cpu
Requires-Dist: onnx; extra == "onnx-cpu"
Requires-Dist: onnxruntime; extra == "onnx-cpu"
Provides-Extra: onnx-gpu
Requires-Dist: onnx; extra == "onnx-gpu"
Requires-Dist: onnxruntime-gpu; extra == "onnx-gpu"
Provides-Extra: wandb
Requires-Dist: wandb; extra == "wandb"
Provides-Extra: dev
Requires-Dist: isort; extra == "dev"
Requires-Dist: black; extra == "dev"
Requires-Dist: ruff; extra == "dev"
Requires-Dist: pre-commit; extra == "dev"
Requires-Dist: tuna; extra == "dev"
Requires-Dist: twine; extra == "dev"
Provides-Extra: docs
Requires-Dist: jupyter-book; extra == "docs"
Provides-Extra: test
Requires-Dist: pytest; extra == "test"
Requires-Dist: pytest_qt; extra == "test"
Requires-Dist: pytest-cov; extra == "test"
Requires-Dist: coverage; extra == "test"
Requires-Dist: tox; extra == "test"
Requires-Dist: twine; extra == "test"
Requires-Dist: onnx; extra == "test"
Requires-Dist: onnxruntime; extra == "test"
